{
  "cors": 1,
  "백엔드-마일스톤": 1,
  "operation_system": 6,
  "computer_science": 27,
  "computer_architecture": 7,
  "hardware": 6,
  "database": 2,
  "sql": 1,
  "mysql": 1,
  "java": 11,
  "math": 1,
  "software_engineering": 2,
  "사색": 4,
  "생각_기록_통찰": 4,
  "2023마일드스톤": 1,
  "생각정리": 1,
  "군중심리": 2,
  "algorithm": 10,
  "sorting": 7,
  "hash": 3,
  "aws": 2,
  "ec2": 1,
  "infra": 2,
  "lambda": 1,
  "spring": 11,
  "스프링-삼각형": 1,
  "gradle": 1,
  "bean": 1,
  "jpa": 2,
  "spring_security": 4,
  "지구방위대": 1,
  "트러블슈팅": 1,
  "스프링": 1,
  "network": 1,
  "operating-system": 2,
  "side-project": 2,
  "pintos": 2,
  "project": 4,
  "backend": 4,
  "architecture": 10,
  "한권으로_읽는_컴퓨터_구조와_프로그래밍": 10,
  "nextgen": 1,
  "game": 2,
  "code_complete": 8,
  "software": 8
}
